wattrex_driver_rs/__init__.py
wattrex_driver_rs/__version__.py
wattrex_driver_rs/drv_rs.py
wattrex_driver_rs-0.0.1.dist-info/LICENSE.txt
wattrex_driver_rs-0.0.1.dist-info/METADATA
wattrex_driver_rs-0.0.1.dist-info/WHEEL
wattrex_driver_rs-0.0.1.dist-info/top_level.txt
wattrex_driver_rs-0.0.1.dist-info/RECORD
